tenform/__init__.py
tenform/cli.py
tenform/tenform.py
tenform/utils.py
tenform-0.1.5.dist-info/METADATA
tenform-0.1.5.dist-info/RECORD
tenform-0.1.5.dist-info/WHEEL
tenform-0.1.5.dist-info/entry_points.txt
tenform-0.1.5.dist-info/top_level.txt
