Metadata-Version: 2.1
Name: tenform
Version: 0.1.5
Summary: RPython package that utilizes requests and regex to make digging through the SEC database eand analyzing 10 forms easy.
Home-page: https://github.com/tyfal/tenform
Author: Tyler F.
Author-email: tyfal647@gmail.com
License: MIT license
Keywords: tenform
Platform: UNKNOWN
Classifier: Development Status :: 2 - Pre-Alpha
Classifier: Intended Audience :: Developers
Classifier: License :: OSI Approved :: MIT License
Classifier: Natural Language :: English
Classifier: Programming Language :: Python :: 2
Classifier: Programming Language :: Python :: 2.7
Classifier: Programming Language :: Python :: 3
Classifier: Programming Language :: Python :: 3.4
Classifier: Programming Language :: Python :: 3.5
Classifier: Programming Language :: Python :: 3.6
Requires-Dist: Click (>=6.0)
Requires-Dist: regex
Requires-Dist: requests (>=2.19.1)
Requires-Dist: bs4 (>=0.0.1)
